httpanalyzer/__init__.py
httpanalyzer/src.py
httpanalyzer/utils.py
httpanalyzer/lists/__init__.py
httpanalyzer-0.1.6.dist-info/LICENSE.txt
httpanalyzer-0.1.6.dist-info/METADATA
httpanalyzer-0.1.6.dist-info/WHEEL
httpanalyzer-0.1.6.dist-info/top_level.txt
httpanalyzer-0.1.6.dist-info/RECORD
