Metadata-Version: 2.1
Name: httpanalyzer
Version: 0.1.6
Summary: Library for analyzing http-requests
Author-email: Martin Merkli <martin.merkli@protonmail.com>
License: MIT License
Project-URL: homepage, https://github.com/MartinMerkli/httpanalyzer
Project-URL: repository, https://github.com/MartinMerkli/httpanalyzer
Keywords: python,http
Classifier: License :: OSI Approved :: MIT License
Classifier: Operating System :: OS Independent
Classifier: Programming Language :: Python :: 3
Classifier: Intended Audience :: Developers
Classifier: Intended Audience :: System Administrators
Requires-Python: >=3.6
License-File: LICENSE.txt
